mnemoreg/__init__.py
mnemoreg/_types.py
mnemoreg/core.py
mnemoreg/exceptions.py
mnemoreg/_storage/__init__.py
mnemoreg/_storage/base.py
mnemoreg/_storage/memory.py
mnemoreg/_storage/protocol.py
mnemoreg-0.3.9.dist-info/licenses/LICENSE
mnemoreg-0.3.9.dist-info/METADATA
mnemoreg-0.3.9.dist-info/WHEEL
mnemoreg-0.3.9.dist-info/top_level.txt
mnemoreg-0.3.9.dist-info/RECORD
